digitalClock/__init__.py
digitalClock/digital_clock.py
digitalclockkel5-0.0.1.dist-info/LICENCE.txt
digitalclockkel5-0.0.1.dist-info/METADATA
digitalclockkel5-0.0.1.dist-info/WHEEL
digitalclockkel5-0.0.1.dist-info/top_level.txt
digitalclockkel5-0.0.1.dist-info/RECORD
