Metadata-Version: 2.1
Name: digitalclockkel5
Version: 0.0.1
Summary: Library Digital Clock menyediakan kemampuan untuk menampilkan jam digital yang dapat disesuaikan dengan mudah dalam aplikasi berbasis Tkinter.
Home-page: https://github.com/codewithwan/digital-clock
Author: codewithwan
Author-email: <codewithwan@gmail.com>
License: MIT
Keywords: Digital,Clock
Classifier: Development Status :: 1 - Planning
License-File: LICENCE.txt
